vml/__init__.py
vml/extract_features.py
vml/localize_sfm.py
vml/match_features.py
vml/pairs_from_exhaustive.py
vml/pairs_from_retrieval.py
vml/reconstruction.py
vml/triangulation.py
vml/visualization.py
vml/extractors/__init__.py
vml/extractors/netvlad.py
vml/extractors/superpoint.py
vml/matchers/__init__.py
vml/matchers/nearest_neighbor.py
vml/matchers/superglue.py
vml/utils/__init__.py
vml/utils/base_model.py
vml/utils/database.py
vml/utils/dataset.py
vml/utils/geometry.py
vml/utils/io.py
vml/utils/parsers.py
vml/utils/read_write_model.py
vml/utils/tools.py
vml/utils/viz.py
vml/utils/viz_3d.py
visual_mapping_localization-1.3.dist-info/METADATA
visual_mapping_localization-1.3.dist-info/WHEEL
visual_mapping_localization-1.3.dist-info/top_level.txt
visual_mapping_localization-1.3.dist-info/RECORD
